liblogging/__init__.py
liblogging/logger.py
liblogging/util.py
liblogging/sending/__init__.py
liblogging/sending/kafka_service.py
liblogging/sending/log_collector.py
liblogging-0.1.15.dist-info/licenses/LICENSE
liblogging-0.1.15.dist-info/METADATA
liblogging-0.1.15.dist-info/WHEEL
liblogging-0.1.15.dist-info/entry_points.txt
liblogging-0.1.15.dist-info/top_level.txt
liblogging-0.1.15.dist-info/zip-safe
liblogging-0.1.15.dist-info/RECORD
