Metadata-Version: 2.4
Name: liblogging
Version: 0.1.15
Summary: Utilities for logging and sending logs.
Home-page: https://github.com/XoriieInpottn/liblogging
Author: xi
Author-email: gylv@mail.ustc.edu.cn, huangfuyb@163.com
License: Apache-2.0 license
Platform: any
Classifier: Programming Language :: Python :: 3
License-File: LICENSE
Provides-Extra: collector
Requires-Dist: kafka-python==2.0.2; extra == "collector"
Dynamic: author
Dynamic: author-email
Dynamic: classifier
Dynamic: description
Dynamic: description-content-type
Dynamic: home-page
Dynamic: license
Dynamic: license-file
Dynamic: platform
Dynamic: provides-extra
Dynamic: summary
